LICENSE.rst
MANIFEST.in
README.rst
setup.py
src/oset/__init__.py
src/oset/_abc.py
src/oset/pyoset.py
src/oset/tests.py
src/oset.egg-info/PKG-INFO
src/oset.egg-info/SOURCES.txt
src/oset.egg-info/dependency_links.txt
src/oset.egg-info/namespace_packages.txt
src/oset.egg-info/requires.txt
src/oset.egg-info/top_level.txt
src/oset.egg-info/zip-safe