Metadata-Version: 1.0
Name: oset
Version: 0.1.2
Summary: Ordered Set.
Home-page: https://gitorious.com/sleipnir/python-oset
Author: Carlos Martin
Author-email: inean.es@gmail.com
License: Python Software Foundation License
Keywords: oset ordered set collection
Platform: UNKNOWN
Classifier: Development Status :: 4 - Beta
Classifier: License :: OSI Approved :: Python Software Foundation License
Classifier: Operating System :: OS Independent
Classifier: Programming Language :: Python
Classifier: Topic :: Software Development
